{
"type": "FeatureCollection",
"name": "Chch_CBD_Urban_2024_2025 - Imagery_Centres",
"crs": { "type": "name", "properties": { "name": "urn:ogc:def:crs:OGC:1.3:CRS84" } },
"xy_coordinate_resolution": 1e-15,
"features": [
{ "type": "Feature", "properties": { "Project": "PGRM3214", "Company_Name": null, "SN_No": null, "Description": null, "OrthoGSD_m": null, "PointDensity_(points/m2)": null, "Area": 16.428784782529391, "Percentage_Coverage": 100.0 }, "geometry": { "type": "Point", "coordinates": [ 172.633188973115608, -43.529833881374174 ] } }
]
}
